{
	"configurations" : 
	[
		{
			"directories" : 
			[
				{
					"build" : ".",
					"minimumCMakeVersion" : 
					{
						"string" : "3.0"
					},
					"projectIndex" : 0,
					"source" : ".",
					"targetIndexes" : 
					[
						0
					]
				}
			],
			"name" : "",
			"projects" : 
			[
				{
					"directoryIndexes" : 
					[
						0
					],
					"name" : "Renderer",
					"targetIndexes" : 
					[
						0
					]
				}
			],
			"targets" : 
			[
				{
					"directoryIndex" : 0,
					"id" : "Renderer::@6890427a1f51a3e7e1df",
					"jsonFile" : "target-Renderer-76762f0887944f6a911a.json",
					"name" : "Renderer",
					"projectIndex" : 0
				}
			]
		}
	],
	"kind" : "codemodel",
	"paths" : 
	{
		"build" : "/Users/wenjian_zhou/Program/cpp/Renderer/build",
		"source" : "/Users/wenjian_zhou/Program/cpp/Renderer"
	},
	"version" : 
	{
		"major" : 2,
		"minor" : 2
	}
}
